README.rst
setup.py
bin/__init__.py
bin/helloWorld.py
helloAaron/__init__.py
helloAaron/welcome.py
helloAaron.egg-info/PKG-INFO
helloAaron.egg-info/SOURCES.txt
helloAaron.egg-info/dependency_links.txt
helloAaron.egg-info/not-zip-safe
helloAaron.egg-info/top_level.txt