Metadata-Version: 1.1
Name: helloAaron
Version: 0.3
Summary: Python package example
Home-page: http://aarontuor.site
Author: Aaron Tuor
Author-email: aarontuor@gmail.com
License: MIT
Keywords: Package Distribution
Platform: UNKNOWN
Classifier: Programming Language :: Python
